MANIFEST.in
README.rst
setup.py
FunnyBonesProject.egg-info/PKG-INFO
FunnyBonesProject.egg-info/SOURCES.txt
FunnyBonesProject.egg-info/dependency_links.txt
FunnyBonesProject.egg-info/top_level.txt
Jokes/__init__.py
Jokes/joke.py