Metadata-Version: 1.0
Name: FunnyBonesProject
Version: 1.0.2
Summary: Example package that tells a joke
Home-page: UNKNOWN
Author: Abhijit Baxi
Author-email: baxiabhijit@gmail.com
License: MIT
Platform: UNKNOWN
